py_name_entity_recognition/__init__.py
py_name_entity_recognition/catalog.py
py_name_entity_recognition/core/__init__.py
py_name_entity_recognition/core/engine.py
py_name_entity_recognition/data_handling/__init__.py
py_name_entity_recognition/data_handling/chunking.py
py_name_entity_recognition/data_handling/io.py
py_name_entity_recognition/data_handling/merging.py
py_name_entity_recognition/models/__init__.py
py_name_entity_recognition/models/config.py
py_name_entity_recognition/models/factory.py
py_name_entity_recognition/observability/__init__.py
py_name_entity_recognition/observability/logging.py
py_name_entity_recognition/observability/visualization.py
py_name_entity_recognition/prompting/__init__.py
py_name_entity_recognition/prompting/prompt_manager.py
py_name_entity_recognition/schemas/__init__.py
py_name_entity_recognition/schemas/core_schemas.py
py_name_entity_recognition/utils/__init__.py
py_name_entity_recognition/utils/biores_converter.py
py_name_entity_recognition-1.0.8.dist-info/METADATA
py_name_entity_recognition-1.0.8.dist-info/WHEEL
py_name_entity_recognition-1.0.8.dist-info/licenses/LICENSE
py_name_entity_recognition-1.0.8.dist-info/licenses/NOTICE
py_name_entity_recognition-1.0.8.dist-info/RECORD
