Metadata-Version: 2.4
Name: py_name_entity_recognition
Version: 1.0.8
Summary: LLM-based Named Entity Recognition using LangChain and LangGraph
License: Apache-2.0
License-File: LICENSE
License-File: NOTICE
Keywords: ner,named entity recognition,llm,langchain,langgraph,nlp
Author: Gowtham Rao
Author-email: rao@ohdsi.org
Requires-Python: >=3.10,<4.0
Classifier: License :: OSI Approved :: Apache Software License
Classifier: Operating System :: MacOS
Classifier: Operating System :: Microsoft :: Windows
Classifier: Operating System :: POSIX :: Linux
Classifier: Programming Language :: Python :: 3
Classifier: Programming Language :: Python :: 3.10
Classifier: Programming Language :: Python :: 3.11
Classifier: Programming Language :: Python :: 3.12
Classifier: Programming Language :: Python :: 3.13
Classifier: Programming Language :: Python :: 3.14
Requires-Dist: Jinja2 (>=3.1.0,<4.0.0)
Requires-Dist: anthropic (>=0.23.0,<0.24.0)
Requires-Dist: datasets (>=2.14.0,<3.0.0)
Requires-Dist: google-generativeai (>=0.3.0,<0.4.0)
Requires-Dist: langchain (>=0.2.0,<0.3.0)
Requires-Dist: langchain-anthropic (>=0.1.0,<0.2.0)
Requires-Dist: langchain-community (>=0.2.0,<0.3.0)
Requires-Dist: langchain-openai (>=0.1.0,<0.2.0)
Requires-Dist: langgraph (>=0.1.0,<0.2.0)
Requires-Dist: loguru (>=0.7.0,<0.8.0)
Requires-Dist: numpy (>=1.22.4,<2.0.0)
Requires-Dist: ollama (>=0.1.0,<0.2.0)
Requires-Dist: openai (>=1.3.0,<2.0.0)
Requires-Dist: pandas (>=2.0,<3.0)
Requires-Dist: pydantic (>=2.5.0,<3.0.0)
Requires-Dist: python-dotenv (>=1.0.0,<2.0.0)
Requires-Dist: pyyaml (>=6.0,<7.0)
Requires-Dist: spacy (>=3.7.0,<4.0.0)
Requires-Dist: tenacity (>=8.2.0,<9.0.0)
Requires-Dist: toml (>=0.10.2,<0.11.0)
Project-URL: Homepage, https://github.com/OHDSI/py_name_entity_recognition
Project-URL: Repository, https://github.com/OHDSI/py_name_entity_recognition
